Henson_Database-0.5.0.dist-info/DESCRIPTION.rst
Henson_Database-0.5.0.dist-info/METADATA
Henson_Database-0.5.0.dist-info/RECORD
Henson_Database-0.5.0.dist-info/WHEEL
Henson_Database-0.5.0.dist-info/metadata.json
Henson_Database-0.5.0.dist-info/top_level.txt
henson_database/__init__.py
henson_database/templates/henson/alembic.ini.mako
henson_database/templates/henson/env.py
henson_database/templates/henson/script.py.mako
