Metadata-Version: 2.0
Name: Henson-Database
Version: 0.5.0
Summary: A library for using SQLAlchemy with a Henson application
Home-page: https://henson-database.readthedocs.io
Author: Andy Dirnberger, Jon Banafato, Leonard Bedner, and others
Author-email: henson@iheart.com
License: Apache License, Version 2.0
Platform: UNKNOWN
Classifier: Development Status :: 4 - Beta
Classifier: Intended Audience :: Developers
Classifier: License :: OSI Approved :: Apache Software License
Classifier: Natural Language :: English
Classifier: Operating System :: POSIX
Classifier: Programming Language :: Python
Classifier: Programming Language :: Python :: 3.8
Classifier: Programming Language :: Python :: 3.9
Classifier: Programming Language :: Python :: 3 :: Only
Classifier: Topic :: Software Development :: Libraries :: Application Frameworks
Provides-Extra: migrations
Requires-Dist: Henson (>=1.1)
Requires-Dist: SQLAlchemy (>=1.0.2)
Provides-Extra: migrations
Requires-Dist: alembic; extra == 'migrations'
